mac_appgen/__main__.py
mac_appgen/copyfiles.py
mac_appgen/genskel.py
mac_appgen/getdep.py
mac_appgen/getinfo.py
mac_appgen/iconproc.py
mac_appgen/infoplist.py
mac_appgen/structs.py
mac_appgen-1.0.0.dist-info/METADATA
mac_appgen-1.0.0.dist-info/WHEEL
mac_appgen-1.0.0.dist-info/licenses/LICENSE
mac_appgen-1.0.0.dist-info/RECORD
